{
    "invocations": [
        {
            "name": "Ascendent Step",
            "desc": "I can cast Levitate on myself at will."
        },
        {
            "name": "Agonizing Blast",
            "desc": "I add my charisma modifier to Eldritch Blast damage."
        },
        {
            "name": "Book of Ancient Secrets",
            "desc": "I can inscribe rituals in my Book of Shadows. Rituals can be from any class's spell list, can only be cast as rituals, and must be of a level equal to or less than half of my warlock level (rounded up)."
        },
        {
            "name": "Eldritch Spear",
            "desc": "My Eldritch Blast has a range of 300 feet."
        },
        {
            "name": "Grasp of Hadar",
            "desc": "Once per turn when I hit a creature with Eldritch Blast, I can move that creature 10 feet straight toward me."
        },
        {
            "name": "Mask of Many Faces",
            "desc": "I can cast 'disguise self' at will without expending a spell slot."
        },
        {
            "name": "Repelling Blast",
            "desc": "When I hit a creature with Eldritch Blast, I can push them 10 feet away from me."
        },
        {
            "name": "Visions of Distant Realms",
            "desc": "I can cast 'arcane eye' at will without expending a spell slot."
        }
    ]
}
